safdie/__init__.py
safdie/command.py
safdie/command_runner.py
safdie/finder.py
safdie/tests/__init__.py
safdie/tests/test_command.py
safdie/tests/test_command_runner.py
safdie-2.0.4.dist-info/LICENSE
safdie-2.0.4.dist-info/METADATA
safdie-2.0.4.dist-info/WHEEL
safdie-2.0.4.dist-info/top_level.txt
safdie-2.0.4.dist-info/RECORD
